argparse_ps1/__init__.py
argparse_ps1/argparse_ps1.py
argparse_ps1/py.typed
argparse_ps1-0.1.6.dist-info/METADATA
argparse_ps1-0.1.6.dist-info/WHEEL
argparse_ps1-0.1.6.dist-info/licenses/LICENSE
argparse_ps1-0.1.6.dist-info/RECORD
