Metadata-Version: 2.4
Name: argparse-ps1
Version: 0.1.6
Summary: Generate PowerShell wrapper scripts for Python scripts executed with uv
Project-URL: Homepage, https://github.com/shimarch/argparse-ps1
Project-URL: Repository, https://github.com/shimarch/argparse-ps1
Project-URL: Issues, https://github.com/shimarch/argparse-ps1/issues
Project-URL: Documentation, https://github.com/shimarch/argparse-ps1#readme
Author: Shimarch
License: MIT
License-File: LICENSE
Keywords: cli,code-generation,powershell,uv,wrapper
Classifier: Development Status :: 4 - Beta
Classifier: Intended Audience :: Developers
Classifier: License :: OSI Approved :: MIT License
Classifier: Operating System :: OS Independent
Classifier: Programming Language :: Python :: 3
Classifier: Programming Language :: Python :: 3.11
Classifier: Programming Language :: Python :: 3.12
Classifier: Programming Language :: Python :: 3.13
Classifier: Topic :: Software Development :: Code Generators
Classifier: Topic :: System :: Shells
Classifier: Typing :: Typed
Requires-Python: >=3.11
